mdslides/__init__.py
mdslides/cli.py
mdslides/converter.py
mdslides_typst-0.1.2.dist-info/METADATA
mdslides_typst-0.1.2.dist-info/WHEEL
mdslides_typst-0.1.2.dist-info/entry_points.txt
mdslides_typst-0.1.2.dist-info/RECORD
