Metadata-Version: 2.4
Name: mdslides-typst
Version: 0.1.2
Summary: Convert Markdown to PDF slides using Typst and typslides
License: MIT
Requires-Python: >=3.12
Requires-Dist: click
Requires-Dist: rich
